nb_serverproxy_openrefine/__init__.py
nb_serverproxy_openrefine/icons/openrefine.svg
nb_serverproxy_openrefine-0.0.9.dist-info/LICENSE
nb_serverproxy_openrefine-0.0.9.dist-info/METADATA
nb_serverproxy_openrefine-0.0.9.dist-info/WHEEL
nb_serverproxy_openrefine-0.0.9.dist-info/entry_points.txt
nb_serverproxy_openrefine-0.0.9.dist-info/top_level.txt
nb_serverproxy_openrefine-0.0.9.dist-info/RECORD
