Metadata-Version: 2.1
Name: nb-serverproxy-openrefine
Version: 0.0.9
Summary: Jupyter server proxy wrapper for Open Refine
Home-page: https://github.com/innovationOUtside/nb_serverproxy_openrefine
Author: Tony Hirst
License-File: LICENSE
Requires-Dist: jupyter-server-proxy
